{"session_id": "0a4002eb-85d5-4b5d-87c3-000ba55d1eb8", "order_id": "b4cdc9af-32e6-46c1-95dc-12247434ad81", "user_id": "f2d816cd-f0b0-4295-a459-fc85cb7940c9", "items": [{"product_id": "SKU-00952", "quantity": 2, "price": 45.95}], "order_status": "cancelled", "order_time": "2026-02-11T19:39:28.743767+00:00", "ingest_time": "2026-02-11T19:39:41.882661+00:00"}
{"session_id": "9b2a597c-c878-4653-8f3c-310a2f0f1268", "order_id": "f73b450e-23aa-40c0-9a03-5dc15375232a", "user_id": "8288230b-9355-4e15-94b3-686211d9e8de", "items": [{"product_id": "SKU-00636", "quantity": 1, "price": 6.99}], "order_status": "cancelled", "order_time": "2026-02-11T19:39:39.544506+00:00", "ingest_time": "2026-02-11T19:39:41.882661+00:00"}
{"session_id": "04c62900-746a-457e-b422-af600fa4e5f8", "order_id": "0de89777-3d53-4cad-88d1-a775e555f7bc", "user_id": "ebad988b-248d-440b-833e-1c8b47e317ad", "items": [{"product_id": "SKU-00194", "quantity": 3, "price": 7.99}], "order_status": "completed", "order_time": "2026-02-11T19:39:37.977403+00:00", "ingest_time": "2026-02-11T19:39:41.882661+00:00"}
{"session_id": "4213c150-f0c8-4f4a-bac4-1a8ae1fd7ed0", "order_id": "3c1a81f5-a65f-46f9-986c-f76a51139402", "user_id": "6ebdb06e-0d54-485d-995c-baf3244fa83f", "items": [{"product_id": "SKU-00822", "quantity": 1, "price": 7.99}, {"product_id": "SKU-00903", "quantity": 4, "price": 18.95}, {"product_id": "SKU-00369", "quantity": 4, "price": 38.95}], "order_status": "completed", "order_time": "2026-02-11T19:39:37.643498+00:00", "ingest_time": "2026-02-11T19:39:41.882661+00:00"}
{"session_id": "cd5ffbb1-987f-4114-bd01-6d3ef04e888d", "order_id": "5425b114-12f4-4f2b-995d-5ef6ffdf23aa", "user_id": "dea3f901-074f-4ff1-8143-b1abb20e70e5", "items": [{"product_id": "SKU-00506", "quantity": 2, "price": 95.49}, {"product_id": "SKU-00340", "quantity": 3, "price": 8.99}], "order_status": "pending", "order_time": "2026-02-11T19:39:32.110887+00:00", "ingest_time": "2026-02-11T19:39:41.882661+00:00"}
