{"session_id": "c3290e8e-f402-4d2c-ab6b-a0280d04639b", "order_id": "acefffab-f331-496d-95cc-d7b211a00176", "user_id": "eed2d39e-a51f-46a7-8205-6c1fae159dd7", "items": [{"product_id": "SKU-00380", "quantity": 4, "price": 43.95}], "order_status": "pending", "order_time": "2026-02-11T19:42:11.082633+00:00", "ingest_time": "2026-02-11T19:42:13.308254+00:00"}
{"session_id": "a29f1fdf-1e96-40a8-a4dc-2fb667bb0d3b", "order_id": "48088695-a37f-490b-8272-8f6504e3822e", "user_id": "ee70733e-5ed4-4b3e-8adf-8ba6ed64b52f", "items": [{"product_id": "SKU-01418", "quantity": 5, "price": 12.95}], "order_status": "completed", "order_time": "2026-02-11T19:41:49.003491+00:00", "ingest_time": "2026-02-11T19:42:13.308254+00:00"}
{"session_id": "77333c2f-cb6d-4282-9d89-7d225c678500", "order_id": "de616e6c-d931-400a-83dd-34e1f40c1d85", "user_id": "bb9e720d-923b-4c85-9f4f-da0f203bf34a", "items": [{"product_id": "SKU-00571", "quantity": 4, "price": 10.95}, {"product_id": "SKU-00471", "quantity": 1, "price": 57.49}], "order_status": "cancelled", "order_time": "2026-02-11T19:41:49.535036+00:00", "ingest_time": "2026-02-11T19:42:13.308254+00:00"}
