{"session_id": "dc6df396-1ba6-46f4-aa61-5cf2ebe6d6a4", "order_id": "a453af8a-b73f-4145-91c5-508e059d607c", "user_id": "80e3e2cf-7cd5-407b-a734-38cc9a943033", "items": [{"product_id": "SKU-00647", "quantity": 6, "price": 10.95}], "order_status": "completed", "order_time": "2026-02-11T19:39:51.814192+00:00", "ingest_time": "2026-02-11T19:39:57.007935+00:00"}
{"session_id": "95bfee13-4c7c-4d67-a211-fcdef40e4319", "order_id": "cbb53c27-d975-4058-bd2d-db15e907c041", "user_id": "6e331cdb-dd08-4f82-81d8-0dce49b75ce3", "items": [{"product_id": "SKU-00140", "quantity": 2, "price": 115.49}, {"product_id": "SKU-01325", "quantity": 6, "price": 30.95}], "order_status": "pending", "order_time": "2026-02-11T19:39:44.793189+00:00", "ingest_time": "2026-02-11T19:39:57.007935+00:00"}
{"session_id": "0baa5007-fef2-4cf2-875f-ea4194293252", "order_id": "61667cde-77d6-4aff-aac3-961acbff6fbe", "user_id": "f3aaee1c-0864-42c4-b7a9-8d87d1d1c5db", "items": [{"product_id": "SKU-00674", "quantity": 6, "price": 76.49}, {"product_id": "SKU-01280", "quantity": 5, "price": 17.95}], "order_status": "completed", "order_time": "2026-02-11T19:39:48.578919+00:00", "ingest_time": "2026-02-11T19:39:57.007935+00:00"}
{"session_id": "126ebe83-c1db-47a9-8181-5384411bfd41", "order_id": "fc61b38c-b71b-4393-b53e-23a615fdb7cf", "user_id": "7d2b3787-6ce7-491e-b907-ee0cd06e0c22", "items": [{"product_id": "SKU-00586", "quantity": 5, "price": 30.95}, {"product_id": "SKU-00394", "quantity": 1, "price": 29.95}], "order_status": "pending", "order_time": "2026-02-11T19:39:36.628542+00:00", "ingest_time": "2026-02-11T19:39:57.007935+00:00"}
